AbstractInterpretation/README.md
AbstractInterpretation/__init__.py
AbstractInterpretation/__main__.py
AbstractInterpretation/file.epub
AbstractInterpretation/index.html
AbstractInterpretation/css/__init__.py
AbstractInterpretation/css/annotations.css
AbstractInterpretation/css/main.css
AbstractInterpretation/css/normalize.css
AbstractInterpretation/css/popup.css
AbstractInterpretation/font/__init__.py
AbstractInterpretation/font/fontello.eot
AbstractInterpretation/font/fontello.svg
AbstractInterpretation/font/fontello.ttf
AbstractInterpretation/font/fontello.woff
AbstractInterpretation/img/__init__.py
AbstractInterpretation/img/annotator-glyph-sprite.png
AbstractInterpretation/img/annotator-icon-sprite.png
AbstractInterpretation/img/apple-touch-icon.png
AbstractInterpretation/img/cancelfullscreen.png
AbstractInterpretation/img/close.png
AbstractInterpretation/img/fullscreen.png
AbstractInterpretation/img/loader.gif
AbstractInterpretation/img/menu-icon.png
AbstractInterpretation/img/save.png
AbstractInterpretation/img/saved.png
AbstractInterpretation/img/settings-s.png
AbstractInterpretation/img/settings.png
AbstractInterpretation/img/star.png
AbstractInterpretation/js/__init__.py
AbstractInterpretation/js/epub.js
AbstractInterpretation/js/epub.min.js
AbstractInterpretation/js/epub.min.map
AbstractInterpretation/js/hooks.min.js
AbstractInterpretation/js/hooks.min.map
AbstractInterpretation/js/reader.js
AbstractInterpretation/js/reader.js.map
AbstractInterpretation/js/reader.min.js
AbstractInterpretation/js/reader.min.map
AbstractInterpretation/js/hooks/__init__.py
AbstractInterpretation/js/hooks/extensions/__init__.py
AbstractInterpretation/js/hooks/extensions/highlight.js
AbstractInterpretation/js/libs/__init__.py
AbstractInterpretation/js/libs/jquery.min.js
AbstractInterpretation/js/libs/localforage.min.js
AbstractInterpretation/js/libs/screenfull.js
AbstractInterpretation/js/libs/screenfull.min.js
AbstractInterpretation/js/libs/zip.min.js
abstract_interpretation-2024.3.1.0.dist-info/METADATA
abstract_interpretation-2024.3.1.0.dist-info/WHEEL
abstract_interpretation-2024.3.1.0.dist-info/entry_points.txt
abstract_interpretation-2024.3.1.0.dist-info/top_level.txt
abstract_interpretation-2024.3.1.0.dist-info/RECORD
